arguer/__init__.py
arguer/arguer.py
arguer-0.1.1.dist-info/METADATA
arguer-0.1.1.dist-info/WHEEL
arguer-0.1.1.dist-info/RECORD
