Metadata-Version: 2.3
Name: arguer
Version: 0.1.1
Summary: Customizable drop-in replacement for argparse
Author: Danny Stewart
Author-email: danny@stewart.cc
Requires-Python: >=3.12
Classifier: Programming Language :: Python :: 3
Classifier: Programming Language :: Python :: 3.12
Classifier: Programming Language :: Python :: 3.13
Requires-Dist: devpkg (>=0.2.0)
